ImagePipe-0.2.0rc1.dist-info/DESCRIPTION.rst
ImagePipe-0.2.0rc1.dist-info/METADATA
ImagePipe-0.2.0rc1.dist-info/RECORD
ImagePipe-0.2.0rc1.dist-info/WHEEL
ImagePipe-0.2.0rc1.dist-info/metadata.json
ImagePipe-0.2.0rc1.dist-info/top_level.txt
examples/Aksay_pipeline_2.py
examples/Kristen_pipeline.py
examples/__init__.py
examples/akshay_pipeline.py
examples/akshay_support.py
examples/kristen_support.py
examples/linhao_pipeline.py
examples/linhao_support.py
examples/xi_pipeline.py
examples/xi_support.py
imagepipe/__init__.py
imagepipe/core_functions.py
imagepipe/debug_renders.py
imagepipe/density_plot.py
imagepipe/iterate_and_check_img_files.py
imagepipe/raw_functions.py
imagepipe/renders.py
imagepipe/traversals.py
imagepipe/wrapped_functions.py
imagepipe/tools/__init__.py
imagepipe/tools/helpers.py
unittests/TestAll.py
unittests/__init__.py
